filestorage_predeployed/__init__.py
filestorage_predeployed/address.py
filestorage_predeployed/filestorage_generator.py
filestorage_predeployed/artifacts/FileStorage.json
filestorage_predeployed/artifacts/FileStorage.meta.json
filestorage_predeployed-1.1.0.dev8.dist-info/METADATA
filestorage_predeployed-1.1.0.dev8.dist-info/WHEEL
filestorage_predeployed-1.1.0.dev8.dist-info/top_level.txt
filestorage_predeployed-1.1.0.dev8.dist-info/RECORD
