Metadata-Version: 2.1
Name: filestorage-predeployed
Version: 1.1.0.dev8
Summary: A tool for generating predeployed filestorage smart contract
Home-page: https://github.com/skalenetwork/filestorage
Author: SKALE Labs
Author-email: support@skalelabs.com
License: UNKNOWN
Keywords: skale,filestorage,predeployed
Platform: UNKNOWN
Classifier: Development Status :: 5 - Production/Stable
Classifier: Intended Audience :: Developers
Classifier: License :: OSI Approved :: GNU Affero General Public License v3 or later (AGPLv3+)
Classifier: Natural Language :: English
Classifier: Programming Language :: Python :: 3.7
Requires-Python: >=3.7,<4
Requires-Dist: predeployed-generator (>=1.1.0)
Provides-Extra: dev
Requires-Dist: flake8 (==3.7.9) ; extra == 'dev'
Requires-Dist: twine (==3.1.1) ; extra == 'dev'
Provides-Extra: linter
Requires-Dist: flake8 (==3.7.9) ; extra == 'linter'
